lanceotron/__init__.py
lanceotron/cli.py
lanceotron/lanceotron.py
lanceotron/modules.py
lanceotron/utils.py
lanceotron/static/__init__.py
lanceotron/static/standard_scaler_deep_v5_03.p
lanceotron/static/standard_scaler_wide_v5_03.p
lanceotron/static/wide_and_deep_fully_trained_v5_03.h5
lanceotron-1.2.7.dist-info/LICENSE
lanceotron-1.2.7.dist-info/METADATA
lanceotron-1.2.7.dist-info/WHEEL
lanceotron-1.2.7.dist-info/entry_points.txt
lanceotron-1.2.7.dist-info/top_level.txt
lanceotron-1.2.7.dist-info/RECORD
