Metadata-Version: 2.1
Name: lanceotron
Version: 1.2.7
Summary: Command-line interface to the lanceotron deep learning peak caller
Author: Chris Cole, Lance Hentges, Simone G. Riva
Author-email: simo.riva15@gmail.com
Project-URL: Bug Tracker, https://github.com/LHentges/lanceotron/issues
Project-URL: Source, https://github.com/LHentges/lanceotron
Keywords: deep learning,peak calling,keras
Requires-Python: >=3.7
License-File: LICENSE
Requires-Dist: pyBigWig
Requires-Dist: scikit-learn
Requires-Dist: numpy
Requires-Dist: pandas
Requires-Dist: tensorflow >2
Requires-Dist: scipy
Requires-Dist: natsort
Requires-Dist: tqdm
